sheepdoge/__init__.py
sheepdoge/__version__.py
sheepdoge/app.py
sheepdoge/cli.py
sheepdoge/config.py
sheepdoge/exception.py
sheepdoge/kennel.py
sheepdoge/pup.py
sheepdoge/utils.py
sheepdoge/action/__init__.py
sheepdoge/action/install.py
sheepdoge/action/run.py
sheepdoge-0.2.1.dist-info/LICENSE
sheepdoge-0.2.1.dist-info/METADATA
sheepdoge-0.2.1.dist-info/WHEEL
sheepdoge-0.2.1.dist-info/entry_points.txt
sheepdoge-0.2.1.dist-info/top_level.txt
sheepdoge-0.2.1.dist-info/RECORD
